repominer/__init__.py
repominer/files.py
repominer/filters.py
repominer/utils.py
repominer/metrics/__init__.py
repominer/metrics/ansible.py
repominer/metrics/base.py
repominer/metrics/tosca.py
repominer/mining/__init__.py
repominer/mining/ansible.py
repominer/mining/ansible_modules.py
repominer/mining/base.py
repominer/mining/rules.py
repominer/mining/tosca.py
tests/metrics/__init__.py
tests/metrics/test_ansible.py
tests/metrics/test_base.py
tests/metrics/test_tosca.py
tests/mining/__init__.py
tests/mining/test_ansible_fixing_commit_classifier.py
tests/mining/test_ansible_miner.py
tests/mining/test_base_fixing_commit_classifier.py
tests/mining/test_base_miner.py
tests/mining/test_rules.py
tests/mining/test_tosca_miner.py
repository_miner-1.0.4.dist-info/LICENSE
repository_miner-1.0.4.dist-info/METADATA
repository_miner-1.0.4.dist-info/WHEEL
repository_miner-1.0.4.dist-info/top_level.txt
repository_miner-1.0.4.dist-info/RECORD
