Metadata-Version: 2.1
Name: repository-miner
Version: 1.0.4
Summary: A tool to mine software repositories for defect prediction.
Home-page: https://github.com/radon-h2020/radon-repository-miner
Download-URL: https://github.com/radon-h2020/radon-repository-miner/archive/1.0.4.tar.gz
Author: Stefano Dalla Palma
Author-email: stefano.dallapalma0@gmail.com
Maintainer: Stefano Dalla Palma
License: Apache License
Classifier: Development Status :: 5 - Production/Stable
Classifier: Intended Audience :: Developers
Classifier: Programming Language :: Python :: 3.6
Classifier: Programming Language :: Python :: 3.7
Classifier: Programming Language :: Python :: 3.8
Classifier: Programming Language :: Python :: 3.9
Classifier: License :: OSI Approved :: Apache Software License
Classifier: Topic :: Software Development :: Libraries :: Python Modules
Classifier: Operating System :: POSIX :: Linux
Requires-Python: >=3.6
License-File: LICENSE
Requires-Dist: ansiblemetrics
Requires-Dist: dataclasses ~=0.6
Requires-Dist: nltk ~=3.5
Requires-Dist: pandas ~=1.1.4
Requires-Dist: pydriller ~=2.5
Requires-Dist: pyyaml ~=6.0.1
Requires-Dist: spacy ~=2.3.4
Requires-Dist: tosca-metrics ~=0.0.8
